petsctools/__init__.py
petsctools/citation.py
petsctools/config.py
petsctools/exceptions.py
petsctools/init.py
petsctools/options.py
petsctools/utils.py
petsctools-2025.2.dist-info/licenses/LICENSE
petsctools-2025.2.dist-info/METADATA
petsctools-2025.2.dist-info/WHEEL
petsctools-2025.2.dist-info/top_level.txt
petsctools-2025.2.dist-info/RECORD
