Metadata-Version: 2.4
Name: petsctools
Version: 2025.2
Summary: Pythonic extensions for petsc4py and slepc4py
Maintainer-email: "Connor J. Ward" <c.ward20@imperial.ac.uk>
License-Expression: LGPL-3.0-or-later
Project-URL: Repository, https://github.com/firedrakeproject/petsctools
Classifier: Intended Audience :: Science/Research
Classifier: Programming Language :: Python
Classifier: Programming Language :: Python :: 3
Classifier: Operating System :: Unix
Requires-Python: >=3.10
License-File: LICENSE
Requires-Dist: packaging
Provides-Extra: petsc4py
Requires-Dist: petsc4py; extra == "petsc4py"
Provides-Extra: slepc4py
Requires-Dist: slepc4py; extra == "slepc4py"
Dynamic: license-file
